fofa_hack/__init__.py
fofa_hack/fofa.py
tookit/__init__.py
tookit/config.py
tookit/fofaUseragent.py
tookit/levelData.py
tookit/outputData.py
tookit/sign.py
tookit/unit.py
tookit/urlRequest.py
fofa_hack-0.0.2.dist-info/LICENSE
fofa_hack-0.0.2.dist-info/METADATA
fofa_hack-0.0.2.dist-info/WHEEL
fofa_hack-0.0.2.dist-info/top_level.txt
fofa_hack-0.0.2.dist-info/RECORD
