Metadata-Version: 2.1
Name: fofa-hack
Version: 0.0.2
Summary: fofa hack
Home-page: https://github.com/Cl0udG0d/Fofa-hack
Author: Cl0udG0d
Author-email: 
Classifier: Programming Language :: Python :: 3
Classifier: License :: OSI Approved :: GNU General Public License (GPL)
Classifier: Operating System :: OS Independent
Requires-Python: >=3.6
License-File: LICENSE
